odoo8_addon_l10n_ch_base_bank-8.0.1.2.0.99.dev26-nspkg.pth
odoo_addons/l10n_ch_base_bank/README.rst
odoo_addons/l10n_ch_base_bank/__init__.py
odoo_addons/l10n_ch_base_bank/__openerp__.py
odoo_addons/l10n_ch_base_bank/bank.py
odoo_addons/l10n_ch_base_bank/bank_data.xml
odoo_addons/l10n_ch_base_bank/bank_view.xml
odoo_addons/l10n_ch_base_bank/invoice.py
odoo_addons/l10n_ch_base_bank/i18n/ar.po
odoo_addons/l10n_ch_base_bank/i18n/bg.po
odoo_addons/l10n_ch_base_bank/i18n/bs.po
odoo_addons/l10n_ch_base_bank/i18n/ca.po
odoo_addons/l10n_ch_base_bank/i18n/ca_ES.po
odoo_addons/l10n_ch_base_bank/i18n/cs.po
odoo_addons/l10n_ch_base_bank/i18n/de.po
odoo_addons/l10n_ch_base_bank/i18n/el_GR.po
odoo_addons/l10n_ch_base_bank/i18n/en_GB.po
odoo_addons/l10n_ch_base_bank/i18n/es.po
odoo_addons/l10n_ch_base_bank/i18n/es_CR.po
odoo_addons/l10n_ch_base_bank/i18n/es_EC.po
odoo_addons/l10n_ch_base_bank/i18n/es_MX.po
odoo_addons/l10n_ch_base_bank/i18n/es_PE.po
odoo_addons/l10n_ch_base_bank/i18n/et.po
odoo_addons/l10n_ch_base_bank/i18n/eu.po
odoo_addons/l10n_ch_base_bank/i18n/fi.po
odoo_addons/l10n_ch_base_bank/i18n/fr.po
odoo_addons/l10n_ch_base_bank/i18n/fr_CH.po
odoo_addons/l10n_ch_base_bank/i18n/gl.po
odoo_addons/l10n_ch_base_bank/i18n/hr.po
odoo_addons/l10n_ch_base_bank/i18n/hr_HR.po
odoo_addons/l10n_ch_base_bank/i18n/id.po
odoo_addons/l10n_ch_base_bank/i18n/it.po
odoo_addons/l10n_ch_base_bank/i18n/ja.po
odoo_addons/l10n_ch_base_bank/i18n/l10n_ch_base_bank.pot
odoo_addons/l10n_ch_base_bank/i18n/lt.po
odoo_addons/l10n_ch_base_bank/i18n/mk.po
odoo_addons/l10n_ch_base_bank/i18n/mn.po
odoo_addons/l10n_ch_base_bank/i18n/nb_NO.po
odoo_addons/l10n_ch_base_bank/i18n/nl.po
odoo_addons/l10n_ch_base_bank/i18n/nl_BE.po
odoo_addons/l10n_ch_base_bank/i18n/nl_NL.po
odoo_addons/l10n_ch_base_bank/i18n/pl.po
odoo_addons/l10n_ch_base_bank/i18n/pt.po
odoo_addons/l10n_ch_base_bank/i18n/pt_BR.po
odoo_addons/l10n_ch_base_bank/i18n/pt_PT.po
odoo_addons/l10n_ch_base_bank/i18n/ro.po
odoo8_addon_l10n_ch_base_bank-8.0.1.2.0.99.dev26.dist-info/METADATA
odoo8_addon_l10n_ch_base_bank-8.0.1.2.0.99.dev26.dist-info/WHEEL
odoo8_addon_l10n_ch_base_bank-8.0.1.2.0.99.dev26.dist-info/namespace_packages.txt
odoo8_addon_l10n_ch_base_bank-8.0.1.2.0.99.dev26.dist-info/top_level.txt
odoo8_addon_l10n_ch_base_bank-8.0.1.2.0.99.dev26.dist-info/RECORD
